girder_utils/__init__.py
girder_utils/admin.py
girder_utils/allauth.py
girder_utils/apps.py
girder_utils/db.py
girder_utils/files.py
girder_utils/py.typed
girder_utils/rest_framework.py
girder_utils/storages.py
girder_utils/templatetags/__init__.py
girder_utils/templatetags/girder_utils.py
django_girder_utils-0.13.1.dist-info/LICENSE
django_girder_utils-0.13.1.dist-info/METADATA
django_girder_utils-0.13.1.dist-info/WHEEL
django_girder_utils-0.13.1.dist-info/top_level.txt
django_girder_utils-0.13.1.dist-info/RECORD
