Metadata-Version: 2.1
Name: django-girder-utils
Version: 0.13.1
Summary: Django utilities for data management applications.
Home-page: https://github.com/girder/django-girder-utils
Author: Kitware, Inc.
Author-email: kitware@kitware.com
License: Apache 2.0
Project-URL: Bug Reports, https://github.com/girder/django-girder-utils/issues
Project-URL: Source, https://github.com/girder/django-girder-utils
Keywords: django girder
Classifier: Development Status :: 3 - Alpha
Classifier: Environment :: Web Environment
Classifier: Framework :: Django :: 3.2
Classifier: Framework :: Django :: 4
Classifier: Framework :: Django :: 4.0
Classifier: Framework :: Django :: 4.1
Classifier: Framework :: Django
Classifier: Intended Audience :: Developers
Classifier: License :: OSI Approved :: Apache Software License
Classifier: Operating System :: OS Independent
Classifier: Programming Language :: Python :: 3
Classifier: Programming Language :: Python :: 3.8
Classifier: Programming Language :: Python :: 3.9
Classifier: Programming Language :: Python :: 3.10
Classifier: Programming Language :: Python
Requires-Python: >=3.8
License-File: LICENSE
Requires-Dist: django (>=3.2)
Provides-Extra: allauth
Requires-Dist: django-allauth ; extra == 'allauth'
Provides-Extra: boto3_storage
Requires-Dist: django-storages[boto3] ; extra == 'boto3_storage'
Provides-Extra: minio_storage
Requires-Dist: django-minio-storage ; extra == 'minio_storage'
Provides-Extra: rest_framework
Requires-Dist: djangorestframework ; extra == 'rest_framework'
